README.md
setup.cfg
setup.py
cocotbext/apb/__init__.py
cocotbext/apb/address_space.py
cocotbext/apb/apb_base.py
cocotbext/apb/apb_bus.py
cocotbext/apb/apb_master.py
cocotbext/apb/apb_monitor.py
cocotbext/apb/apb_ram.py
cocotbext/apb/apb_slave.py
cocotbext/apb/buddy_allocator.py
cocotbext/apb/constants.py
cocotbext/apb/memory.py
cocotbext/apb/sparse_memory.py
cocotbext/apb/utils.py
cocotbext/apb/version.py
cocotbext_apb.egg-info/PKG-INFO
cocotbext_apb.egg-info/SOURCES.txt
cocotbext_apb.egg-info/dependency_links.txt
cocotbext_apb.egg-info/requires.txt
cocotbext_apb.egg-info/top_level.txt